Metadata-Version: 2.1
Name: raygun-tap-autopilot
Version: 0.3.1
Summary: Singer.io tap for extracting data from the Autopilot API
Home-page: https://raygun.com
Author: Raygun
Author-email: luke@raygun.com
License: UNKNOWN
Platform: UNKNOWN
Classifier: Programming Language :: Python :: 3 :: Only
Provides-Extra: dev
